{"dineshkumar.d@cgvakindia.com":"","deepa_anantha@yahoo.com":"","sark@sarkware.com":"","parthibnboxing@gmail.com":"","zarishkhosa@gmail.com":"","kailas@iamkailas.com":"","lilybeee@outlook.fr":"","support@support.digitalocean.com":"","noreply@limewebdevelopment.com":"","support@github.com":"","paynet@billdesk.in":"","weloveourdevs@shopify.com":"","cesaregonzi@gmail.com":"","Ganesh.M@airtel.com":"","steven_liu@mail.vsell.com.tw":"","info@twitter.com":"","iljf@lfrqqhjdy.com":"","eseafoodsin@gmail.com":"","jyxy@sajan.com":"","eperz@glx.net":"","wordpress@sarkware.com":"","jobs-listings@linkedin.com":"","xf@qsfcjht.org":"","messages-noreply@linkedin.com":"","noreply@updates.freelancer.com":"","paypal@e.paypal.com":"","feedback@slack.com":"","mmcgufficke@daviesbaird.com.au":"","no-reply@slack.com":"","Statements@sbicard.com":"","info@airtelupdate.com":"","wpdunning@gmail.com":"","noam@cleanforest.co":"","welovepartners@shopify.com":"","service@intl.paypal.com":"","member@paypal.co.in":"","kb6673@gmail.com":"","support@mvaayoo.com":"","business7@mvaayoo.com":"","cardprotection@cppindia.com":"","wordpress@eseafoods.in":"","iman@fastcargo.com.cn":"","business8@mvaayoo.com":"","rud.konstantyn@gmail.com":"","storenvy@going2learn.net":"","keir@shopify.com":"","slekshmipriya@gmail.com":"","no-reply@dropbox.com":"","overseas11@tgshipping.net":"","Barlow76@rr.com":"","naren@stockroom.io":"","weloveourpartners@shopify.com":"","ngf678@hotmail.com":"","invitation-do-not-reply@trello.com":"","taco@trello.com":"","no_reply@amazon.com":"","digital-no-reply@amazon.in":"","account-update@amazon.in":"","do-not-reply@amazon.com":"","desimone.cristina@gmail.com":"","kindernest.india@gmail.com":"","noreply@github.com":"","rinkuc@visualbi.com":"","ati@alamtimur.com.my":"","pierre.wiberg@kircherrodewiberg.se":"","contactmurli@gmail.com":"","store-news@amazon.in":"","orders@livedgy.com":"","emmett_harris3@yahoo.com":"","deepaananth@glocalnet.net":"","hello@devwebsites.com":"","ramsrikumar53@gmail.com":"","adrian.knight15@gmail.com":"","support@linode.com":"","billing@linode.com":"","connect@oligarcy.in":"","notifications@github.com":"","do-not-reply@envato.com":"","colm@wedigital.email":"","lic_eps@licindia.com":"","awl-in.pgoperations@atos.net":"","no-reply@dropboxmail.com":"","support@wowslider.com":"","murli@savivatech.com":"","contactjammy@gmail.com":"","info@go.digitalocean.com":"","notifications-noreply@bitbucket.org":"","marcusltorres@gmail.com":"","courtney.symons@shopify.com":"","roni078723@gmail.com":"","gitlab@mg.gitlab.com":"","noreply@linode.com":"","bala@sarkware.com":"","Mailer-Daemon@md-in-31.webhostbox.net":"","hemnath@hemzware.com":"","itsmesark@gmail.com":"","no_reply@globalsign.com":"","info@e.twitter.com":"","noreply@notifications.freelancer.com":"","aadhaar@uidai.gov.in":"","paypal@mail.paypal.com":"","andrea.klein@superpioneerorigin.com":"","info@sbicapsec.com":"","news@gitlab.com":"","michael@nylas.com":"","jobs-noreply@linkedin.com":"","bayandchelle@bigpond.com":"","k@alzanki.com":"","pranavak2016@outlook.com":"","debitcards@sbi.co.in":"","mybuddy@sbi.co.in":"","mail@change.org":"","do-not-reply@market.envato.com":"","newsletter@ewebdesign.com":"","priya@emphasisconsultants.com":"","anjuannievarghese@gmail.com":"","samardeep1376@outlook.com":"","Gateway.VPC@mastercard.com":"","notify@twitter.com":"","onlinemail@hdfclifeinsured.com":"","varun@shopifygenius.com":"","lpsadmin@idmail.lenovo.com":"","business8@mvaayoo.net":"","ishaqa@onenaturehotels.com":"","randy.murray@ripnet.com":"","response@lenovoservices.net":"","pop@lenovo.com":"","tbukah@gmail.com":"","mingtat.chew@gmail.com":"","ragnar@bros.is":"","no-reply@email.payoneer.messages3.com":"","support@apycom.net":"","anup.velpula@gmail.com":"","donotreply@obc.co.in":"","mgubendran@gmail.com":"","account-security-noreply@account.microsoft.com":"","do-not-reply-wlinipg@worldline.com":"","tristanjay@me.com":"","khalil.antoun@gmail.com":"","guchi.aasif@gmail.com":"","betzer@sayitonasign.com":"","MicrosoftOffice365@email.office.com":"","no-reply@cleartrip.com":"","ckyc@sbicapsec.com":"","web@credenceindia.com":"","zaleskis.m@gmail.com":"","design@lubm.education":"","ibabebabe@gmail.com":"","brendan@djsa.co.za":"","info@odoo.com":"","danielgz@antiun.com":"","jbrousse@club-internet.fr":"","dan@dlsbusinesssolutions.co.uk":"","invitations@linkedin.com":"","postmaster@info.cleartrip.com":"","applecambria@gmail.com":"","noreply@freelancer.com":"","delhi.tmr@nic.in":"","no-reply@curlinit.com":"","info@tc-equipment.de":"","sbichairman@sbi.co.in":"","news@linkedin.com":"","sgganesh@gmail.com":"","donotreply@blackberry.com":"","andrew000us@gmail.com":"","atul@openlogicsys.com":"","DONOTREPLY@incometaxindiaefiling.gov.in":"","jason@thebestagency.com":"","sark@msconsortium.co.in":"","payal.rastgio@gmail.com":"","sonja.bush@setcontactszone.com":"","info@webservicedelhi.com":"","socialmedia@sbi.co.in":"","email@info.digitalocean.com":"","jinnnnij@gmail.com":"","ryanseeley@sbcglobal.net":"","kian@staggeringdesign.com":"","notifications-noreply@linkedin.com":"","matthew.v@personaldatingassistants.com":"","mohanras89@gmail.com":"","deal@123phonecall.com":"","robertp@ocoosbusiness.com":"","jack@webhot-solutions.com":"","php2ranjan@hotmail.com":"","preeti.k@waltdrive.com":"","ann@globaldirectservices.com":"","mail@businessburner.com":"","jaspreet.singh123345@hotmail.com":"","abby.seolink4@outlook.com":"","sale@promoflight.biz":"","pauldavisgomes@outlook.com":"","hello@browserstack.com":"","earl.thomson@amoraime.com":"","clinton.joseph@rusengineers.ru":"","nomination@sbicapsec.com":"","no-reply@statebankrewardz.com":"","hello@newleaflabs.com":"","Marketing.homeloans@sbi.co.in":"","store_news@amazon.in":"","":"","mohsen.lgvm@gmail.com":"","helmar@mrmasterkey.com":"","dush88gs@gmail.com":"","Amex@123phonecall.com":"","do-not-reply@goair.in":"","brooks@thetrophyhouseinc.com":"","linkedin@e.linkedin.com":"","Prasuna.Barik@unilever.com":"","Jagath.M@unilever.com":"","madhusudhanprm@gmail.com":"","coverfox@omoto.io":"","donotreply@bajajallianz.co.in":"","help@coverfox.com":"","nmims@123phonecall.com":"","Microsoft@123phonecall.com":"","info@currentstand.com":"","thorsten.p.rohde@gmail.com":"","zrf@gmail.com":"","dpl@123phonecall.com":"","mycholan@ymail.com":"","support+kit@shopify.com":"","notify@alerts.coverfox.com":"","TAX@123phonecall.com":"","alice.providerweb@hotmail.com":"","fnwummxdse@32270-23911.cloudwaysapps.com":"","coolwinks@123phonecall.com":"","ww1.admin@nutramaxlabs.info":"","rizwan2020@gmail.com":"","frankmbewa@mynet.com":"","manuelehaisek@gmail.com":"","HDFC.Life@123phonecall.com":"","darren@vatu.co.uk":"","malavika.prav@gmail.com":"","varunsridharan23@gmail.com":"","jaimie.au@gmail.com":"","jphennebert@pcsos.be":"","christian@hallshosting.co.uk":"","dzainein@gmail.com":"","morissettep1971@gmail.com":"","thom@fingerlakes1.com":"","gfouhost@rsb21.rhostbh.com":"","paranjothi@sarkware.com":""}